flask_awscognito/__init__.py
flask_awscognito/constants.py
flask_awscognito/exceptions.py
flask_awscognito/plugin.py
flask_awscognito/utils.py
flask_awscognito/services/__init__.py
flask_awscognito/services/cognito_service.py
flask_awscognito/services/token_service.py
tests/__init__.py
tests/conftest.py
tests/test_cognito_service.py
tests/test_plugin.py
tests/test_token_service.py
Flask_AWSCognito-1.3.dist-info/LICENSE
Flask_AWSCognito-1.3.dist-info/METADATA
Flask_AWSCognito-1.3.dist-info/WHEEL
Flask_AWSCognito-1.3.dist-info/top_level.txt
Flask_AWSCognito-1.3.dist-info/RECORD
