Metadata-Version: 2.1
Name: Flask-AWSCognito
Version: 1.3
Summary: Authenticate users with AWS Cognito
Home-page: https://github.com/cgauge/Flask-AWSCognito/
Author: CustomerGauge
Author-email: python@customergauge.com
License: MIT
Platform: any
Classifier: Environment :: Web Environment
Classifier: Intended Audience :: Developers
Classifier: License :: OSI Approved :: BSD License
Classifier: Operating System :: OS Independent
Classifier: Programming Language :: Python :: 3
Classifier: Topic :: Internet :: WWW/HTTP :: Dynamic Content
Classifier: Topic :: Software Development :: Libraries :: Python Modules
Requires-Python: >=3.6
Provides-Extra: tests
